pshmodule/__init__.py
pshmodule/db/__init__.py
pshmodule/db/alchemy.py
pshmodule/db/config.py
pshmodule/processing/__init__.py
pshmodule/processing/processing.py
pshmodule/selenium/__init__.py
pshmodule/selenium/helper.py
pshmodule/utils/__init__.py
pshmodule/utils/filemanager.py
pshmodule-0.1.14.dist-info/METADATA
pshmodule-0.1.14.dist-info/WHEEL
pshmodule-0.1.14.dist-info/top_level.txt
pshmodule-0.1.14.dist-info/RECORD
