Metadata-Version: 2.1
Name: pshmodule
Version: 0.1.14
Summary: Modules related to preprocessing, crawling, collection, database, data load & save 
Home-page: https://github.com/hipster4020/package-module
Author: shpark610
Author-email: hipster4020@gmail.com
Classifier: Programming Language :: Python :: 3
Classifier: Operating System :: OS Independent
Requires-Python: >=3.8
Requires-Dist: sqlalchemy
Requires-Dist: webdriver-manager
Requires-Dist: selenium
Requires-Dist: openpyxl
Requires-Dist: jamo
